LICENSE
MANIFEST.in
README.rst
setup.cfg
setup.py
get_weather_data.egg-info/PKG-INFO
get_weather_data.egg-info/SOURCES.txt
get_weather_data.egg-info/dependency_links.txt
get_weather_data.egg-info/entry_points.txt
get_weather_data.egg-info/requires.txt
get_weather_data.egg-info/top_level.txt
noaaweb/README.md
noaaweb/__init__.py
noaaweb/noaaweb.py
noaaweb/samplein.csv
noaaweb/sampleout.csv
zip2wd/README.md
zip2wd/__init__.py
zip2wd/column-names-info.txt
zip2wd/column-names.txt
zip2wd/demographics2input.py
zip2wd/manager.py
zip2wd/sample-input-basic.csv
zip2wd/sample-input-extend.csv
zip2wd/worker.py
zip2wd/zip2wd.cfg
zip2wd/zip2wd.py
zip2wd/data/import-db.sh
zip2ws/__init__.py
zip2ws/readme.md
zip2ws/zip2ws.py
zip2ws/data/dummy.txt