Metadata-Version: 1.1
Name: get-weather-data
Version: 0.1.31
Summary: Scripts for finding out the weather in a particular zip code
Home-page: https://github.com/soodoku/get-weather-data
Author: Suriyan Laohaprapanon, Gaurav Sood
Author-email: suriyant@gmail.com, gsood07@gmail.com
License: MIT
Keywords: weather zip cdo noaa
Platform: UNKNOWN
Classifier: Development Status :: 3 - Alpha
Classifier: Intended Audience :: Developers
Classifier: License :: OSI Approved :: MIT License
Classifier: Programming Language :: Python :: 2.7
Classifier: Topic :: Scientific/Engineering :: Information Analysis
Classifier: Topic :: Software Development :: Libraries :: Python Modules
